[
  { "word": "ชานมไข่มุก", "difficulty": "Easy" },
  { "word": "ส้มตำปูปลาร้า", "difficulty": "Easy" },
  { "word": "หมูกระทะ", "difficulty": "Easy" },
  { "word": "ทุเรียนหมอนทอง", "difficulty": "Easy" },
  { "word": "มาม่ารสต้มยำกุ้ง", "difficulty": "Easy" },
  { "word": "วาซาบิ", "difficulty": "Medium" },
  { "word": "ครัวซองต์", "difficulty": "Medium" },
  { "word": "น้ำพริกหนุ่ม", "difficulty": "Medium" },
  { "word": "ชาบูชิ", "difficulty": "Medium" },
  { "word": "ไอศกรีมกะทิสด", "difficulty": "Medium" },
  { "word": "กาแฟอเมริกาโน่", "difficulty": "Medium" },
  { "word": "ต้มข่าไก่", "difficulty": "Medium" },
  { "word": "บิงซู", "difficulty": "Medium" },
  { "word": "ค็อกเทล", "difficulty": "Hard" },
  { "word": "ซูชิหน้าปลาไหล", "difficulty": "Hard" },
  { "word": "พิซซ่าหน้าฮาวายเอี้ยน", "difficulty": "Hard" },
  { "word": "นมอัดเม็ด", "difficulty": "Hard" },
  { "word": "ไข่เค็มไชยา", "difficulty": "Hard" },
  { "word": "ตับห่าน / Foie Gras", "difficulty": "Hard" },
  { "word": "ขนมเบื้อง", "difficulty": "Hard" }
]
